Workbook

Sheet Instrucciones
B2: Pruebas de la integración Construir ↔ OrbisNet
B3: Guía para marcar en vivo, paso a paso, durante la sesión con el cliente.
B5: Cómo se usa este documento
B6: 1. Llenar primero el cuadro amarillo de abajo: dirección del servidor, llave de API, quién prueba y la fecha.
B7: 2. Ir a la hoja «Casos de prueba». Cada fila es UN paso. Se hacen en orden, de arriba hacia abajo.
B8: 3. La columna «Qué hacer» dice la acción en palabras. La columna «Petición» dice a qué dirección se llama.
B9: 4. En la hoja «Comandos curl» está el comando exacto de cada caso, listo para copiar y pegar en la terminal.
B10: 5. Comparar lo que salió con la columna «Resultado esperado».
B11: 6. Marcar una X en «✔ OK» si salió como dice, o una X en «✘ Falla» si no. Se elige de la lista de la casilla.
B12: 7. Si algo falla, anotarlo en la hoja «Hallazgos» con el número de caso, para no perderlo.
B13: 8. La hoja «Resumen» lleva la cuenta sola: no hay que llenar nada ahí.
B15: Datos del entorno — llenar ANTES de empezar
B16: Dirección del servidor (URL base) | D16: ej. https://api.construir.com
B17: Llave de API — clave (consumer key)
B18: Llave de API — secreto (consumer secret) | D18: no escribirlo completo si el archivo se comparte
B19: Permisos de esa llave | D19: debe ser «lectura y escritura» — ver CP-15
B20: Llave de SOLO LECTURA (para CP-15)
B21: Llave de SOLO ESCRITURA (para CP-15)
B22: Quién ejecuta las pruebas
B23: Quién acompaña por parte del cliente
B24: Fecha de la sesión
B25: Tasa BCV vigente al empezar (y su fecha) | D25: se consulta en GET /exchange-rates/current
B26: SKU del producto de prueba
B27: Existencia (stock) inicial de ese producto
B28: Números de pedido creados hoy | D28: anotarlos TODOS: hay que anularlos al terminar
B30: ⚠ Advertencias importantes
B31: • Los pedidos de prueba DESCUENTAN INVENTARIO REAL. Anotar el número de cada pedido creado y anularlos al terminar.
B32: • Los correos SALEN DE VERDAD, al cliente y al administrador. Usar siempre una dirección propia en el checkout.
B33: • Facturar un pedido (status=completed) dispara el correo de «pago confirmado» al cliente. No hacerlo con el correo de un cliente real.
B34: • Anular un pedido NO envía ningún correo. Si el guion viejo decía lo contrario, ese guion está desactualizado (ver hallazgo H-07).
B35: • Antes de encender el sondeo del ERP, revisar que no queden pedidos viejos en on-hold con impuesto en cero: el ERP les facturaría un IVA que el cliente nunca pagó.
B36: • Las llaves de prueba con permiso de escritura pueden cambiar pedidos reales. Trabajar sólo con los pedidos anotados en el cuadro de arriba.
B37: • Anotar SIEMPRE la existencia del producto antes y después de cada anulación: es la comprobación más importante de todas.
B39: Leyenda de los resultados
B40: Marca | C40: Qué significa | D40: Qué hacer después
B41: X en «✔ OK» | C41: El paso salió exactamente como dice el resultado esperado. | D41: Seguir con el paso siguiente.
B42: X en «✘ Falla» | C42: El resultado fue distinto del esperado. | D42: Anotarlo en la hoja «Hallazgos» con el número de caso y seguir.
B43: Las dos vacías | C43: El paso todavía no se ha probado. | D43: Queda pendiente; el Resumen lo cuenta como «sin probar».
B44: ⚠ en Observaciones | C44: Es un punto que el código no valida o que hay que confirmar en vivo. | D44: Anotar el comportamiento REAL que se vio, aunque el paso pase.
B46: El flujo del ERP, en cuatro pasos
B47: 1. El ERP consulta los pedidos nuevos: GET /api/v1/orders/on-hold?page=1&perPage=10
B48: 2. Registra su orden de compra y confirma: PUT /api/v1/orders/{id} {"status":"pending","order_key":"OC-…"}
B49: 3. Factura: PUT /api/v1/orders/{id} {"status":"completed","order_key":"FAC-…","date_completed":"…"}
B50: 4. Anula: PUT /api/v1/orders/{id} {"status":"cancelled","date_completed":"…"}
B52: Autenticación en TODAS las llamadas: Authorization: Bearer <clave>:<secreto>
B53: Estados posibles del pedido: on-hold → pending → completed | cualquiera de los dos primeros → cancelled

Sheet Casos de prueba
A1: ID | B1: Caso | C1: # Paso | D1: Qué hacer | E1: Petición (método + ruta) | F1: Datos a enviar | G1: Resultado esperado | H1: ✔ OK | I1: ✘ Falla | J1: Observaciones
A2: CP-01 | B2: Nace el pedido y el ERP lo ve en la cola | C2: 1 | D2: Anotar la tasa de cambio vigente ANTES de comprar. Escribir en el papel la tasa y su fecha. | E2: GET {{BASE_URL}}/exchange-rates/current | F2: Sin cuerpo. No hace falta llave de API. | G2: 200 con la tasa (rate) y la fecha de publicación (date). Ojo: la fecha puede ser de días atrás — es la fecha en que el BCV publicó esa tasa, no la de hoy. | J2: Este endpoint es público, lo puede consultar cualquiera.
A3: CP-01 | B3: Nace el pedido y el ERP lo ve en la cola | C3: 2 | D3: En la tienda web, sin iniciar sesión, agregar al carrito 2 unidades de un producto y 1 de otro. Anotar SKU, nombre y precio de cada uno. | E3: Tienda web (navegador) | F3: Productos con IVA normal (16%). | G3: El carrito muestra los 3 artículos. El precio que se ve en el catálogo YA incluye el IVA. | J3: Anotar también la existencia (stock) de cada producto: se compara al final.
A4: CP-01 | B4: Nace el pedido y el ERP lo ve en la cola | C4: 3 | D4: Llenar el checkout como invitado: cédula, nombre, teléfono y un correo PROPIO. Elegir 'Retiro en tienda'. | E4: Tienda web (navegador) | F4: Usar un correo al que se tenga acceso: los correos salen de verdad. | G4: El resumen muestra Base + IVA = Total, y la tasa del BCV con su fecha. | J4: Si el desglose no cuadra en pantalla, detenerse acá y anotarlo.
A5: CP-01 | B5: Nace el pedido y el ERP lo ve en la cola | C5: 4 | D5: Confirmar el pedido. ⚠ Esto descuenta inventario real y dispara correos reales. | E5: POST {{BASE_URL}}/orders (lo hace la tienda sola) | F5: — | G5: Pantalla de confirmación con el número de pedido. Llega el correo al cliente y el aviso al administrador. | J5: ANOTAR el número de pedido (ORD-…) y el id numérico. Se usan en todos los casos siguientes.
A6: CP-01 | B6: Nace el pedido y el ERP lo ve en la cola | C6: 5 | D6: Buscar el pedido en la cola que consume el ERP. | E6: GET {{BASE_URL}}/api/v1/orders/on-hold?page=1&perPage=10 | F6: Cabecera: Authorization: Bearer {{CK}}:{{CS}} | G6: 200. El pedido aparece de PRIMERO (se ordenan del más nuevo al más viejo), con "status": "on-hold" y "number" igual al id.
A7: CP-01 | B7: Nace el pedido y el ERP lo ve en la cola | C7: 6 | D7: Revisar los datos del cliente dentro del pedido. | E7: GET {{BASE_URL}}/api/v1/orders/on-hold?page=1&perPage=10 | F7: Cabecera: Authorization: Bearer {{CK}}:{{CS}} | G7: billing.first_name / last_name / email con lo que se escribió. billing.address_2 y billing.identification = la cédula con su letra (ej. V-12345678). billing.phone con el teléfono, aunque sea retiro en tienda. NINGÚN campo de billing en null: los vacíos van como "". | J7: Un null acá revienta al cliente de OrbisNet; por eso se emiten cadenas vacías.
A8: CP-01 | B8: Nace el pedido y el ERP lo ve en la cola | C8: 7 | D8: Revisar la fecha de creación. | E8: GET {{BASE_URL}}/api/v1/orders/{{ORDER_ID}} | F8: Cabecera: Authorization: Bearer {{CK}}:{{CS}} | G8: date_created en hora local de la tienda (America/Caracas), con formato 2026-08-01T14:35:02. SIN la 'Z' del final y sin desfase horario. | J8: Si aparece con Z o con la hora de Londres, el ERP factura con la hora equivocada.
A9: CP-01 | B9: Nace el pedido y el ERP lo ve en la cola | C9: 8 | D9: Revisar cómo llega el método de entrega. | E9: GET {{BASE_URL}}/api/v1/orders/{{ORDER_ID}} | F9: Cabecera: Authorization: Bearer {{CK}}:{{CS}} | G9: payment_method_title = "Entrega y/o recogida en el local" (retiro) o "Envío a domicilio". | J9: Este campo lleva el método de ENTREGA, no la forma de pago. Es a propósito: el contrato de WooCommerce no tiene otro campo donde ponerlo.
A10: CP-02 | B10: El ERP confirma el pedido (registra su O/C) | C10: 1 | D10: Confirmar la recepción del pedido registrando la orden de compra del ERP. | E10: PUT {{BASE_URL}}/api/v1/orders/{{ORDER_ID}} | F10: {"status":"pending","order_key":"OC-PRUEBA-001"} | G10: 200 con el pedido: status "pending", orderKey = "OC-PRUEBA-001" y purchaseOrderKey = "OC-PRUEBA-001". | J10: La respuesta del PUT viene con los nombres internos (orderKey, purchaseOrderKey), NO en formato WooCommerce. Es normal.
A11: CP-02 | B11: El ERP confirma el pedido (registra su O/C) | C11: 2 | D11: Comprobar que el pedido salió de la cola. | E11: GET {{BASE_URL}}/api/v1/orders/on-hold?page=1&perPage=10 | F11: Cabecera: Authorization: Bearer {{CK}}:{{CS}} | G11: El pedido YA NO aparece en la lista. La cola sólo trae los que están en on-hold.
A12: CP-02 | B12: El ERP confirma el pedido (registra su O/C) | C12: 3 | D12: Consultar el pedido puntual para ver el estado nuevo. | E12: GET {{BASE_URL}}/api/v1/orders/{{ORDER_ID}} | F12: Cabecera: Authorization: Bearer {{CK}}:{{CS}} | G12: 200 con "status": "pending".
A13: CP-02 | B13: El ERP confirma el pedido (registra su O/C) | C13: 4 | D13: Probar el camino alterno con OTRO pedido en on-hold: el endpoint dedicado de confirmación. | E13: PUT {{BASE_URL}}/api/v1/orders/{{ORDER_ID_2}}/acknowledge | F13: {"order_key":"OC-PRUEBA-002"} | G13: 200 y el mismo efecto: pasa a pending con su O/C registrada. | J13: Los dos caminos llaman a la misma función. En producción conviene usar uno solo: el PUT con status=pending.
A14: CP-02 | B14: El ERP confirma el pedido (registra su O/C) | C14: 5 | D14: Revisar los correos. | E14: Bandeja del cliente y del administrador | F14: — | G14: NO llega ningún correo. Confirmar recibo no notifica a nadie.
A15: CP-03 | B15: El ERP factura el pedido | C15: 1 | D15: Anotar la existencia del producto ANTES de facturar. | E15: GET {{BASE_URL}}/api/v1/products/sku/{{SKU}} | F15: Cabecera: Authorization: Bearer {{CK}}:{{CS}} | G15: 200. Anotar el valor de inventory.
A16: CP-03 | B16: El ERP factura el pedido | C16: 2 | D16: Facturar el pedido que quedó en pending. ⚠ Dispara correo real al cliente. | E16: PUT {{BASE_URL}}/api/v1/orders/{{ORDER_ID}} | F16: {"status":"completed","order_key":"OC-PRUEBA-001 / FAC-0001","date_completed":"2026-08-01T15:30:00.000Z"} | G16: 200. status "completed"; dateCompleted con la fecha enviada; orderKey pasa a "OC-PRUEBA-001 / FAC-0001"; purchaseOrderKey SIGUE siendo "OC-PRUEBA-001". | J16: Facturar pisa order_key con el número de factura a propósito; la O/C original queda guardada aparte en purchaseOrderKey.
A17: CP-03 | B17: El ERP factura el pedido | C17: 3 | D17: Revisar el correo del cliente. | E17: Bandeja del correo usado en el checkout | F17: — | G17: Llega el correo "Confirmamos tu pago del pedido ORD-…". | J17: Si el correo falla, la facturación NO se cae: los errores de correo se registran y se ignoran.
A18: CP-03 | B18: El ERP factura el pedido | C18: 4 | D18: Comprobar que facturar NO toca el inventario. | E18: GET {{BASE_URL}}/api/v1/products/sku/{{SKU}} | F18: Cabecera: Authorization: Bearer {{CK}}:{{CS}} | G18: inventory exactamente igual al del paso 1. Facturar no repone ni descuenta stock.
A19: CP-03 | B19: El ERP factura el pedido | C19: 5 | D19: Ver el pedido en el formato del ERP después de facturado. | E19: GET {{BASE_URL}}/api/v1/orders/{{ORDER_ID}} | F19: Cabecera: Authorization: Bearer {{CK}}:{{CS}} | G19: 200 con "status": "completed" y los mismos montos de antes (facturar no recalcula nada).
A20: CP-04 | B20: El ERP anula un pedido y vuelve el inventario | C20: 1 | D20: Crear un pedido de prueba nuevo y confirmarlo con el ERP (repetir CP-01 y CP-02 con la O/C "OC-PRUEBA-003"). ⚠ Descuenta inventario. | E20: Tienda web + PUT {{BASE_URL}}/api/v1/orders/{{ORDER_ID_3}} | F20: {"status":"pending","order_key":"OC-PRUEBA-003"} | G20: El pedido nuevo queda en pending. ANOTAR su id.
A21: CP-04 | B21: El ERP anula un pedido y vuelve el inventario | C21: 2 | D21: Anotar la existencia EXACTA del producto antes de anular. Llamarla E1. | E21: GET {{BASE_URL}}/api/v1/products/sku/{{SKU}} | F21: Cabecera: Authorization: Bearer {{CK}}:{{CS}} | G21: 200. Escribir el número de inventory en el papel.
A22: CP-04 | B22: El ERP anula un pedido y vuelve el inventario | C22: 3 | D22: Anular el pedido. | E22: PUT {{BASE_URL}}/api/v1/orders/{{ORDER_ID_3}} | F22: {"status":"cancelled","date_completed":"2026-08-01T16:00:00.000Z"} | G22: 200. status "cancelled" y dateCompleted con la fecha enviada.
A23: CP-04 | B23: El ERP anula un pedido y vuelve el inventario | C23: 4 | D23: Verificar que el inventario volvió. | E23: GET {{BASE_URL}}/api/v1/products/sku/{{SKU}} | F23: Cabecera: Authorization: Bearer {{CK}}:{{CS}} | G23: inventory = E1 + la cantidad que tenía el pedido. Exacto, ni uno más.
A24: CP-04 | B24: El ERP anula un pedido y vuelve el inventario | C24: 5 | D24: Repetir la MISMA anulación dos veces más seguidas. | E24: PUT {{BASE_URL}}/api/v1/orders/{{ORDER_ID_3}} (×2) | F24: {"status":"cancelled","date_completed":"2026-08-01T16:00:00.000Z"} | G24: 200 las dos veces, y el inventario NO sigue subiendo: se queda en E1 + cantidad. | J24: Es idempotente a propósito. Si el stock sube en cada llamada, es un fallo grave: detener la prueba.
A25: CP-04 | B25: El ERP anula un pedido y vuelve el inventario | C25: 6 | D25: Probar la grafía con una sola L, que es la que documenta OrbisNet, sobre otro pedido. | E25: PUT {{BASE_URL}}/api/v1/orders/{{ORDER_ID_4}} | F25: {"status":"canceled","date_completed":"2026-08-01T16:05:00.000Z"} | G25: 200. Se aceptan las dos escrituras: "canceled" y "cancelled".
A26: CP-04 | B26: El ERP anula un pedido y vuelve el inventario | C26: 7 | D26: Revisar los correos después de anular. | E26: Bandeja del cliente y del administrador | F26: — | G26: NO llega ningún correo, ni al cliente ni al administrador. Las anulaciones las atiende un vendedor por WhatsApp. | J26: ⚠ El guion anterior (docs/guion-pruebas-produccion.md, paso C5) dice que sí llegan correos. El código no manda ninguno. Ver hallazgo H-07.
A27: CP-05 | B27: Consultar un pedido puntual por id y por UUID | C27: 1 | D27: Consultar el pedido por su id numérico. | E27: GET {{BASE_URL}}/api/v1/orders/{{ORDER_ID}} | F27: Cabecera: Authorization: Bearer {{CK}}:{{CS}} | G27: 200 con la forma de WooCommerce: line_items, billing, date_created, total, total_tax. NO devuelve la entidad cruda.
A28: CP-05 | B28: Consultar un pedido puntual por id y por UUID | C28: 2 | D28: Buscar el UUID del pedido en el panel de administración o en la base de datos. | E28: Panel admin / consulta SQL | F28: SELECT id, uuid, order_number FROM orders WHERE id = {{ORDER_ID}}; | G28: Se obtiene el uuid del pedido. | J28: ⚠ El UUID no aparece en ningún campo de la API v1: el ERP no puede descubrirlo por su cuenta. Ver hallazgo H-03.
A29: CP-05 | B29: Consultar un pedido puntual por id y por UUID | C29: 3 | D29: Consultar el mismo pedido por su UUID. | E29: GET {{BASE_URL}}/api/v1/orders/{{ORDER_UUID}} | F29: Cabecera: Authorization: Bearer {{CK}}:{{CS}} | G29: 200 con EXACTAMENTE la misma respuesta del paso 1.
A30: CP-05 | B30: Consultar un pedido puntual por id y por UUID | C30: 4 | D30: Consultar un id que no existe. | E30: GET {{BASE_URL}}/api/v1/orders/999999 | F30: Cabecera: Authorization: Bearer {{CK}}:{{CS}} | G30: 404 con el mensaje "Order 999999 not found".
A31: CP-05 | B31: Consultar un pedido puntual por id y por UUID | C31: 5 | D31: Consultar algo que no es ni id ni UUID. | E31: GET {{BASE_URL}}/api/v1/orders/abc | F31: Cabecera: Authorization: Bearer {{CK}}:{{CS}} | G31: 404, NUNCA 500. | J31: Es una regresión conocida: antes daba 500 porque Postgres no podía convertir el texto a uuid.
A32: CP-06 | B32: Paginación de la cola y cabeceras Link | C32: 1 | D32: Asegurar que hay al menos 3 pedidos en on-hold. Crear los que falten. ⚠ Cada uno descuenta inventario. | E32: Tienda web | F32: — | G32: La cola tiene 3 o más pedidos. | J32: Anotar los números de pedido para anularlos al final.
A33: CP-06 | B33: Paginación de la cola y cabeceras Link | C33: 2 | D33: Pedir la primera página de 2 en 2. | E33: GET {{BASE_URL}}/api/v1/orders/on-hold?page=1&perPage=2 | F33: Cabecera: Authorization: Bearer {{CK}}:{{CS}} | G33: 200. "data" con 2 pedidos; "total" = cantidad real de on-hold; "page": 1; "perPage": 2; "lastPage" = total dividido entre 2, redondeado hacia arriba.
A34: CP-06 | B34: Paginación de la cola y cabeceras Link | C34: 3 | D34: Ver las cabeceras de la respuesta (con curl -i). | E34: GET {{BASE_URL}}/api/v1/orders/on-hold?page=1&perPage=2 | F34: Cabecera: Authorization: Bearer {{CK}}:{{CS}} | G34: Aparece la cabecera Link con rel="next" y rel="last" apuntando a las páginas siguientes. | J34: Formato RFC 5988, el mismo que usa WooCommerce.
A35: CP-06 | B35: Paginación de la cola y cabeceras Link | C35: 4 | D35: Pedir la segunda página. | E35: GET {{BASE_URL}}/api/v1/orders/on-hold?page=2&perPage=2 | F35: Cabecera: Authorization: Bearer {{CK}}:{{CS}} | G35: 200 con pedidos DISTINTOS a los de la página 1, y la cabecera Link ahora con rel="prev" y rel="first".
A36: CP-06 | B36: Paginación de la cola y cabeceras Link | C36: 5 | D36: Pedir una página que no existe. | E36: GET {{BASE_URL}}/api/v1/orders/on-hold?page=999&perPage=2 | F36: Cabecera: Authorization: Bearer {{CK}}:{{CS}} | G36: 200 con "data": [] (lista vacía). No es un error.
A37: CP-06 | B37: Paginación de la cola y cabeceras Link | C37: 6 | D37: Pedir sin parámetros, como haría el ERP por defecto. | E37: GET {{BASE_URL}}/api/v1/orders/on-hold | F37: Cabecera: Authorization: Bearer {{CK}}:{{CS}} | G37: 200 con page 1 y perPage 10 por defecto.
A38: CP-07 | B38: El total del pedido cuadra: base + IVA = total | C38: 1 | D38: Traer el pedido de prueba en formato ERP y anotar total y total_tax. | E38: GET {{BASE_URL}}/api/v1/orders/{{ORDER_ID}} | F38: Cabecera: Authorization: Bearer {{CK}}:{{CS}} | G38: 200. Anotar "total" (con IVA) y "total_tax" (el impuesto del pedido).
A39: CP-07 | B39: El total del pedido cuadra: base + IVA = total | C39: 2 | D39: Sumar a mano los line_items[].total de todas las líneas. | E39: Sobre la misma respuesta | F39: — | G39: La suma da la BASE del pedido, sin IVA. Los renglones del ERP van SIN impuesto: es el contrato de WooCommerce. | J39: Si un renglón trae el precio con IVA incluido, el ERP facturaría 13,8% de más.
A40: CP-07 | B40: El total del pedido cuadra: base + IVA = total | C40: 3 | D40: Sumar a mano los line_items[].total_tax. | E40: Sobre la misma respuesta | F40: — | G40: La suma es IGUAL, al céntimo, al "total_tax" del pedido.
A41: CP-07 | B41: El total del pedido cuadra: base + IVA = total | C41: 4 | D41: Comprobar la identidad principal. | E41: Sobre la misma respuesta | F41: — | G41: Σ line_items.total + Σ line_items.total_tax = total del pedido. Exacto al céntimo, sin diferencias de redondeo. | J41: Sólo se cumple mientras el envío sea 0 (hoy lo es). Ver hallazgo H-13.
A42: CP-07 | B42: El total del pedido cuadra: base + IVA = total | C42: 5 | D42: Contrastar con lo que ve el cliente en el seguimiento público. | E42: GET {{BASE_URL}}/orders/track/{{ORDER_NUMBER}} | F42: Sin llave de API: es público. | G42: subtotal + tax = total. Y subtotal = Σ line_items.total del ERP; tax = Σ line_items.total_tax. | J42: El campo subtotal del pedido es la BASE sin IVA.
A43: CP-07 | B43: El total del pedido cuadra: base + IVA = total | C43: 6 | D43: Revisar la alícuota de cada línea. | E43: GET {{BASE_URL}}/api/v1/orders/{{ORDER_ID}} | F43: Cabecera: Authorization: Bearer {{CK}}:{{CS}} | G43: tax_rate es 16, 8, 0 o 24 exactos. Nunca 16,04 ni 15,98. | J43: El sistema ajusta el cociente a la alícuota nominal más cercana, con 1 punto de tolerancia.
A44: CP-07 | B44: El total del pedido cuadra: base + IVA = total | C44: 7 | D44: Verificar la regla de redondeo en una línea, a mano con la calculadora. | E44: Sobre la misma respuesta | F44: — | G44: base = redondeo a 2 decimales de (monto de la línea con IVA ÷ 1,16); iva = monto con IVA − base. NUNCA se redondean los tres números por separado. | J44: Documentado en docs/pricing-iva.md. Por eso base + iva da el total exacto siempre.
A45: CP-08 | B45: La tasa del pedido es la vigente al momento de la compra | C45: 1 | D45: Antes de comprar, consultar la tasa y anotarla con su fecha. | E45: GET {{BASE_URL}}/exchange-rates/current | F45: Sin llave de API. | G45: 200 con rate (ej. 481,22) y date (ej. 2026-04-19). | J45: La fecha es la de publicación del BCV; puede ser anterior a hoy.
A46: CP-08 | B46: La tasa del pedido es la vigente al momento de la compra | C46: 2 | D46: Crear un pedido de prueba. ⚠ Inventario y correos reales. | E46: Tienda web | F46: — | G46: Pedido creado. Anotar el número.
A47: CP-08 | B47: La tasa del pedido es la vigente al momento de la compra | C47: 3 | D47: Consultar el pedido y comparar la tasa. | E47: GET {{BASE_URL}}/orders/track/{{ORDER_NUMBER}} | F47: Sin llave de API. | G47: exchangeRate = la tasa anotada en el paso 1. exchangeRateDate = la fecha de PUBLICACIÓN del BCV, no la del pedido. | J47: Si exchangeRateDate coincidiera con la fecha del pedido cuando la tasa es vieja, sería un error.
A48: CP-08 | B48: La tasa del pedido es la vigente al momento de la compra | C48: 4 | D48: Revisar el correo de confirmación que le llegó al cliente. | E48: Bandeja del cliente | F48: — | G48: El correo muestra la misma tasa y la misma fecha: "BCV 481,22 · 19 abr".
A49: CP-08 | B49: La tasa del pedido es la vigente al momento de la compra | C49: 5 | D49: Si la tasa se actualiza durante la jornada (o se fuerza una sincronización), volver a consultar el pedido viejo. | E49: GET {{BASE_URL}}/orders/track/{{ORDER_NUMBER}} | F49: Sin llave de API. | G49: El pedido CONSERVA la tasa con la que se compró. Nunca se recalcula. | J49: La tasa se congela al crear el pedido; los pedidos viejos no se tocan.
A50: CP-08 | B50: La tasa del pedido es la vigente al momento de la compra | C50: 6 | D50: Comprobar qué ve el ERP de la tasa. | E50: GET {{BASE_URL}}/api/v1/orders/{{ORDER_ID}} | F50: Cabecera: Authorization: Bearer {{CK}}:{{CS}} | G50: El pedido en formato ERP NO trae ni la tasa ni montos en bolívares: sólo dólares. | J50: ⚠ Si OrbisNet factura en bolívares, la tasa la pone él y puede no ser la del pedido. Ver hallazgo H-02: confirmarlo con el cliente.
A51: CP-09 | B51: Los montos en bolívares cuadran con los dólares por la tasa | C51: 1 | D51: Traer el pedido con sus montos en bolívares. | E51: GET {{BASE_URL}}/orders/track/{{ORDER_NUMBER}} | F51: Sin llave de API. | G51: 200. Anotar subtotalVes, taxVes, totalVes y exchangeRate.
A52: CP-09 | B52: Los montos en bolívares cuadran con los dólares por la tasa | C52: 2 | D52: Comprobar la suma en bolívares. | E52: Con calculadora | F52: — | G52: totalVes = subtotalVes + taxVes, exacto al céntimo.
A53: CP-09 | B53: Los montos en bolívares cuadran con los dólares por la tasa | C53: 3 | D53: Comprobar una línea: monto en dólares × tasa. | E53: Con calculadora | F53: — | G53: items[].subtotalVes ≈ items[].subtotal × tasa, con una diferencia máxima de 1 céntimo por línea (redondeo).
A54: CP-09 | B54: Los montos en bolívares cuadran con los dólares por la tasa | C54: 4 | D54: Sumar los bolívares de todas las líneas. | E54: Con calculadora | F54: — | G54: Σ items[].subtotalVes = totalVes, exacto. | J54: Los agregados salen de sumar las líneas, para que el desglose que ve el cliente cierre.
A55: CP-09 | B55: Los montos en bolívares cuadran con los dólares por la tasa | C55: 5 | D55: Comparar totalVes contra (total en dólares × tasa). | E55: Con calculadora | F55: — | G55: Pueden diferir unos céntimos, y ESTÁ BIEN. Los bolívares se convierten línea por línea, no sobre el total. | J55: Regla documentada en docs/pricing-iva.md. No reportarlo como fallo si la diferencia es de céntimos.
A56: CP-09 | B56: Los montos en bolívares cuadran con los dólares por la tasa | C56: 6 | D56: Pedido muy grande en bolívares. | E56: No probar en vivo | F56: — | G56: Las columnas en bolívares topan en Bs 99.999.999,99. A la tasa de hoy eso son unos USD 207.800. | J56: ⚠ No hacer esta prueba con un pedido real: Postgres responde con error y deja filas huérfanas. Ver hallazgo H-11.
A57: CP-10 | B57: El desglose por ítem suma el total | C57: 1 | D57: Sumar los renglones del seguimiento. | E57: GET {{BASE_URL}}/orders/track/{{ORDER_NUMBER}} | F57: Sin llave de API. | G57: Σ items[].subtotal = total del pedido. Ojo: el subtotal del ítem YA incluye IVA y ya viene con el descuento aplicado.
A58: CP-10 | B58: El desglose por ítem suma el total | C58: 2 | D58: En el formato del ERP, verificar precio × cantidad de cada línea. | E58: GET {{BASE_URL}}/api/v1/orders/{{ORDER_ID}} | F58: Cabecera: Authorization: Bearer {{CK}}:{{CS}} | G58: price × quantity = total de la línea (la base sin IVA). | J58: price va sin redondear a propósito (puede verse 0.9099999999999999). No redondearlo antes de multiplicar o deja de cuadrar.
A59: CP-10 | B59: El desglose por ítem suma el total | C59: 3 | D59: Comparar sku y name de cada línea contra el producto real. | E59: GET {{BASE_URL}}/api/v1/products/sku/{{SKU}} | F59: Cabecera: Authorization: Bearer {{CK}}:{{CS}} | G59: Coinciden. El sku es el que OrbisNet usa para identificar el artículo. | J59: El nombre queda congelado al comprar: si el producto se renombra después, el pedido conserva el nombre viejo. Es correcto.
A60: CP-10 | B60: El desglose por ítem suma el total | C60: 4 | D60: Verificar las cantidades. | E60: Sobre la misma respuesta | F60: — | G60: quantity coincide con lo que se compró en cada renglón.
A61: CP-10 | B61: El desglose por ítem suma el total | C61: 5 | D61: Comprar el MISMO producto en dos renglones distintos y revisar el pedido. ⚠ Pedido real. | E61: GET {{BASE_URL}}/api/v1/orders/{{ORDER_ID_5}} | F61: Cabecera: Authorization: Bearer {{CK}}:{{CS}} | G61: Aparecen DOS renglones, cada uno con su cantidad y su monto. No se colapsan en uno solo ni se repite el monto. | J61: Regresión conocida: antes un mismo producto en dos renglones mostraba el monto de todas las unidades en cada uno.
A62: CP-10 | B62: El desglose por ítem suma el total | C62: 6 | D62: Incluir un producto EXENTO (IVA 0%) en un pedido y revisarlo. | E62: GET {{BASE_URL}}/api/v1/orders/{{ORDER_ID_6}} | F62: Cabecera: Authorization: Bearer {{CK}}:{{CS}} | G62: Esa línea sale con tax_rate 0 y total_tax "0.00". El IVA se calcula línea por línea, con la alícuota propia de cada producto. | J62: Si al exento le aparece IVA, es un fallo grave de facturación.
A63: CP-11 | B63: Pedido con cupón de descuento | C63: 1 | D63: Crear o activar un cupón de prueba en el panel de administración (ej. 10%). | E63: Panel admin | F63: Código sugerido: PRUEBA10 | G63: El cupón queda activo y con usos disponibles.
A64: CP-11 | B64: Pedido con cupón de descuento | C64: 2 | D64: Previsualizar el desglose con el cupón, sin comprar todavía. | E64: POST {{BASE_URL}}/orders/quote | F64: {"items":[{"productUuid":"{{PRODUCT_UUID}}","quantity":2}],"discountCode":"PRUEBA10"} | G64: 200 con el desglose: descuento, base, IVA y total ya rebajado. | J64: Este es el único previsualizador autoritativo. No usar POST /discounts/validate para el monto a cobrar.
A65: CP-11 | B65: Pedido con cupón de descuento | C65: 3 | D65: Comprar aplicando el cupón. ⚠ Pedido real. | E65: Tienda web | F65: — | G65: El pedido se crea con el descuento aplicado. Anotar el número y el id.
A66: CP-11 | B66: Pedido con cupón de descuento | C66: 4 | D66: Revisar el descuento en el seguimiento. | E66: GET {{BASE_URL}}/orders/track/{{ORDER_NUMBER}} | F66: Sin llave de API. | G66: discountAmount = el descuento otorgado. subtotal + tax = total, ya neto del descuento.
A67: CP-11 | B67: Pedido con cupón de descuento | C67: 5 | D67: Revisar cómo le llega el pedido al ERP. | E67: GET {{BASE_URL}}/api/v1/orders/{{ORDER_ID_7}} | F67: Cabecera: Authorization: Bearer {{CK}}:{{CS}} | G67: Las líneas vienen YA rebajadas: el descuento se reparte entre ellas, proporcional al monto de cada una. Σ total + Σ total_tax sigue dando el total del pedido.
A68: CP-11 | B68: Pedido con cupón de descuento | C68: 6 | D68: Revisar que ninguna línea quedó en negativo. | E68: Sobre la misma respuesta | F68: — | G68: Ningún total ni total_tax negativo, ni siquiera con un cupón que cubra casi todo el pedido. | J68: Fue un fallo real: el residuo del reparto dejaba renglones negativos aunque el total del pedido cuadrara.
A69: CP-11 | B69: Pedido con cupón de descuento | C69: 7 | D69: Confirmar con el cliente qué ve OrbisNet del cupón. | E69: GET {{BASE_URL}}/api/v1/orders/{{ORDER_ID_7}} | F69: Cabecera: Authorization: Bearer {{CK}}:{{CS}} | G69: El pedido en formato ERP NO tiene ningún campo de descuento: OrbisNet no puede saber que hubo cupón, sólo ve montos ya rebajados. | J69: ⚠ Hallazgo H-01. Preguntar en la reunión si eso les sirve para su facturación.
A70: CP-11 | B70: Pedido con cupón de descuento | C70: 8 | D70: Probar un cupón que supere el monto del pedido. | E70: POST {{BASE_URL}}/orders/quote | F70: {"items":[{"productUuid":"{{PRODUCT_UUID}}","quantity":1}],"discountCode":"{{CUPON_GRANDE}}"} | G70: El descuento se topea al monto del pedido: el total queda en 0 o más, nunca negativo, y no genera saldo a favor.
A71: CP-11 | B71: Pedido con cupón de descuento | C71: 9 | D71: Probar un cupón vencido o inexistente. | E71: POST {{BASE_URL}}/orders/quote | F71: {"items":[{"productUuid":"{{PRODUCT_UUID}}","quantity":1}],"discountCode":"NOEXISTE"} | G71: 400 con el motivo del rechazo.
A72: CP-12 | B72: Envío a domicilio contra retiro en tienda | C72: 1 | D72: Hacer un pedido eligiendo RETIRO EN TIENDA y revisarlo en el ERP. ⚠ Pedido real. | E72: GET {{BASE_URL}}/api/v1/orders/{{ORDER_ID_8}} | F72: Cabecera: Authorization: Bearer {{CK}}:{{CS}} | G72: payment_method_title = "Entrega y/o recogida en el local". billing.phone con el teléfono del cliente. billing.address_1 y city pueden ir vacíos (""). | J72: El teléfono se toma del cliente, no de la dirección: antes los pedidos de retiro llegaban sin teléfono.
A73: CP-12 | B73: Envío a domicilio contra retiro en tienda | C73: 2 | D73: Hacer un pedido eligiendo ENVÍO A DOMICILIO y revisarlo. ⚠ Pedido real. | E73: GET {{BASE_URL}}/api/v1/orders/{{ORDER_ID_9}} | F73: Cabecera: Authorization: Bearer {{CK}}:{{CS}} | G73: payment_method_title = "Envío a domicilio". billing.address_1 y billing.city con la dirección que se escribió.
A74: CP-12 | B74: Envío a domicilio contra retiro en tienda | C74: 3 | D74: Revisar el costo de envío en los dos pedidos. | E74: GET {{BASE_URL}}/orders/track/{{ORDER_NUMBER}} | F74: Sin llave de API. | G74: shipping = "0.00" en los dos casos: hoy el envío no se cobra. | J74: Está pendiente de implementar; queda en 0 a propósito.
A75: CP-12 | B75: Envío a domicilio contra retiro en tienda | C75: 4 | D75: Confirmar con el cliente qué pasa cuando se active el cobro de envío. | E75: Conversación | F75: — | G75: El pedido en formato ERP no tiene campo ni línea de envío. Cuando se cobre envío, Σ líneas + Σ IVA dejará de dar el total. | J75: ⚠ Hallazgo H-13. Habrá que agregar shipping_total al contrato, como hace WooCommerce.
A76: CP-12 | B76: Envío a domicilio contra retiro en tienda | C76: 5 | D76: Verificar la identificación en el pedido de envío a domicilio. | E76: GET {{BASE_URL}}/api/v1/orders/{{ORDER_ID_9}} | F76: Cabecera: Authorization: Bearer {{CK}}:{{CS}} | G76: billing.address_2 y billing.identification traen la cédula, igual que en el de retiro. | J76: Si el cliente marcó 'crear cuenta', la cédula igual debe salir: se busca en la cuenta, en la ficha de invitado y en la dirección.
A77: CP-13 | B77: Llamar sin llave de API | C77: 1 | D77: Consultar la cola sin ninguna cabecera de autenticación. | E77: GET {{BASE_URL}}/api/v1/orders/on-hold | F77: Sin cabeceras. | G77: 401 con el mensaje "Missing API credentials".
A78: CP-13 | B78: Llamar sin llave de API | C78: 2 | D78: Intentar modificar un pedido sin autenticación. | E78: PUT {{BASE_URL}}/api/v1/orders/{{ORDER_ID}} | F78: {"status":"pending","order_key":"OC-SIN-LLAVE"} | G78: 401. El pedido NO se toca.
A79: CP-13 | B79: Llamar sin llave de API | C79: 3 | D79: Mandar sólo la clave, sin el secreto. | E79: GET {{BASE_URL}}/api/v1/orders/on-hold | F79: Cabecera: Authorization: Bearer {{CK}} | G79: 401 "Missing API credentials". El secreto va después de los dos puntos.
A80: CP-13 | B80: Llamar sin llave de API | C80: 4 | D80: Comprobar que el pedido siguió intacto. | E80: GET {{BASE_URL}}/api/v1/orders/{{ORDER_ID}} | F80: Cabecera: Authorization: Bearer {{CK}}:{{CS}} | G80: El estado del pedido es el mismo de antes de estas pruebas.
A81: CP-14 | B81: Llamar con llave inválida o desactivada | C81: 1 | D81: Usar una clave que no existe. | E81: GET {{BASE_URL}}/api/v1/orders/on-hold | F81: Cabecera: Authorization: Bearer ck_inventada:cs_inventado | G81: 401 con el mensaje "Invalid API credentials".
A82: CP-14 | B82: Llamar con llave inválida o desactivada | C82: 2 | D82: Usar la clave correcta con el secreto equivocado. | E82: GET {{BASE_URL}}/api/v1/orders/on-hold | F82: Cabecera: Authorization: Bearer {{CK}}:secreto-malo | G82: 401 "Invalid API credentials".
A83: CP-14 | B83: Llamar con llave inválida o desactivada | C83: 3 | D83: Desactivar una llave en el panel y volver a usarla. | E83: GET {{BASE_URL}}/api/v1/orders/on-hold | F83: Cabecera con la llave desactivada. | G83: 401 "Invalid API credentials". Una llave desactivada se comporta igual que una que no existe. | J83: Es la palanca para cortarle el acceso al ERP en caliente. Volver a activarla al terminar.
A84: CP-14 | B84: Llamar con llave inválida o desactivada | C84: 4 | D84: Probar la forma alterna de autenticación por cabeceras separadas. | E84: GET {{BASE_URL}}/api/v1/orders/on-hold | F84: Cabeceras: x-consumer-key: {{CK}} y x-consumer-secret: {{CS}} | G84: 200. Es equivalente al Bearer. | J84: ⚠ También se aceptan como parámetros en la URL (?consumer_key=…&consumer_secret=…), pero eso deja las credenciales escritas en los registros del servidor. NO usar esa forma. Hallazgo H-09.
A85: CP-15 | B85: Permisos de la llave: lectura contra escritura | C85: 1 | D85: Con una llave de SOLO LECTURA, consultar la cola. | E85: GET {{BASE_URL}}/api/v1/orders/on-hold | F85: Cabecera con la llave de solo lectura. | G85: 200. Leer sí puede.
A86: CP-15 | B86: Permisos de la llave: lectura contra escritura | C86: 2 | D86: Con la MISMA llave de solo lectura, intentar confirmar un pedido. | E86: PUT {{BASE_URL}}/api/v1/orders/{{ORDER_ID}} | F86: {"status":"pending","order_key":"OC-SOLO-LECTURA"} | G86: 403 con el mensaje "Insufficient permissions". El pedido no cambia.
A87: CP-15 | B87: Permisos de la llave: lectura contra escritura | C87: 3 | D87: Con una llave de SOLO ESCRITURA, intentar consultar la cola. | E87: GET {{BASE_URL}}/api/v1/orders/on-hold | F87: Cabecera con la llave de solo escritura. | G87: 403 "Insufficient permissions". | J87: ⚠ No hay jerarquía: "escritura" NO incluye "lectura". La llave del ERP tiene que ser de lectura y escritura. Hallazgo H-06.
A88: CP-15 | B88: Permisos de la llave: lectura contra escritura | C88: 4 | D88: Con la llave de LECTURA Y ESCRITURA (la del ERP), probar las dos cosas. | E88: GET y PUT sobre {{BASE_URL}}/api/v1/orders/… | F88: Cabecera: Authorization: Bearer {{CK}}:{{CS}} | G88: 200 en las dos. Confirmar que la llave que va a usar OrbisNet en producción es de este tipo. | J88: Anotar en la hoja de Instrucciones qué permiso tiene la llave usada hoy.
A89: CP-16 | B89: Confirmar sin la orden de compra (order_key) | C89: 1 | D89: Intentar confirmar un pedido sin mandar order_key. | E89: PUT {{BASE_URL}}/api/v1/orders/{{ORDER_ID}} | F89: {"status":"pending"} | G89: 400 con el mensaje "order_key is required when status is pending". | J89: El mensaje es claro y dice exactamente qué falta.
A90: CP-16 | B90: Confirmar sin la orden de compra (order_key) | C90: 2 | D90: Intentar con la orden de compra vacía. | E90: PUT {{BASE_URL}}/api/v1/orders/{{ORDER_ID}} | F90: {"status":"pending","order_key":""} | G90: 400. La validación rechaza el texto vacío.
A91: CP-16 | B91: Confirmar sin la orden de compra (order_key) | C91: 3 | D91: Comprobar que el pedido no se movió. | E91: GET {{BASE_URL}}/api/v1/orders/{{ORDER_ID}} | F91: Cabecera: Authorization: Bearer {{CK}}:{{CS}} | G91: Sigue en "on-hold".
A92: CP-17 | B92: Facturar sin los datos obligatorios | C92: 1 | D92: Facturar sin la fecha. | E92: PUT {{BASE_URL}}/api/v1/orders/{{ORDER_ID}} | F92: {"status":"completed","order_key":"FAC-0001"} | G92: 400 "date_completed is required when status is completed".
A93: CP-17 | B93: Facturar sin los datos obligatorios | C93: 2 | D93: Facturar sin el número de factura. | E93: PUT {{BASE_URL}}/api/v1/orders/{{ORDER_ID}} | F93: {"status":"completed","date_completed":"2026-08-01T16:00:00.000Z"} | G93: 400 "order_key is required when status is completed".
A94: CP-17 | B94: Facturar sin los datos obligatorios | C94: 3 | D94: Comprobar que no pasó nada. | E94: GET {{BASE_URL}}/api/v1/orders/{{ORDER_ID}} | F94: Cabecera: Authorization: Bearer {{CK}}:{{CS}} | G94: El pedido sigue en "pending" y NO llegó el correo de pago confirmado.
A95: CP-18 | B95: Anular sin la fecha | C95: 1 | D95: Anular sin mandar date_completed. | E95: PUT {{BASE_URL}}/api/v1/orders/{{ORDER_ID}} | F95: {"status":"cancelled"} | G95: 400 "date_completed is required when status is cancelled".
A96: CP-18 | B96: Anular sin la fecha | C96: 2 | D96: Lo mismo con la grafía de una sola L. | E96: PUT {{BASE_URL}}/api/v1/orders/{{ORDER_ID}} | F96: {"status":"canceled"} | G96: 400 con el mismo mensaje.
A97: CP-18 | B97: Anular sin la fecha | C97: 3 | D97: Comprobar el inventario. | E97: GET {{BASE_URL}}/api/v1/products/sku/{{SKU}} | F97: Cabecera: Authorization: Bearer {{CK}}:{{CS}} | G97: El stock NO se movió: la anulación se rechazó antes de tocar nada.
A98: CP-19 | B98: Trabajar sobre un pedido que no existe | C98: 1 | D98: Confirmar un id inexistente. | E98: PUT {{BASE_URL}}/api/v1/orders/999999 | F98: {"status":"pending","order_key":"OC-FANTASMA"} | G98: 404 "Order with id 999999 not found".
A99: CP-19 | B99: Trabajar sobre un pedido que no existe | C99: 2 | D99: Anular un id inexistente. | E99: PUT {{BASE_URL}}/api/v1/orders/999999 | F99: {"status":"cancelled","date_completed":"2026-08-01T16:00:00.000Z"} | G99: 404 con el mismo tipo de mensaje.
A100: CP-19 | B100: Trabajar sobre un pedido que no existe | C100: 3 | D100: Probar con el id 0. | E100: PUT {{BASE_URL}}/api/v1/orders/0 | F100: {"status":"pending","order_key":"OC-CERO"} | G100: 404: es un número válido, pero no existe ningún pedido 0.
...

Sheet Comandos curl
A1: Caso | B1: Qué hace | C1: Notas | D1: Comando (copiar y pegar)
A2: Antes | B2: Reemplazar los valores entre llaves dobles | C2: {{BASE_URL}} dirección del servidor · {{CK}} clave · {{CS}} secreto · {{ORDER_ID}} id del pedido · {{ORDER_NUMBER}} número ORD-… · {{ORDER_UUID}} uuid · {{SKU}} código del producto · {{PRODUCT_UUID}} uuid del producto | D2: # Todos los comandos suponen que ya se exportaron BASE_URL, CK y CS (ver la fila siguiente).
A3: Autenticación | B3: Todos | C3: Así se autentica cada llamada. La llave del ERP debe tener permiso de lectura Y escritura. | D3: export BASE_URL="https://api.construir.com" export CK="{{CONSUMER_KEY}}" export CS="{{CONSUMER_SECRET}}" # Forma 1 (la que usa OrbisNet): # -H "Authorization: Bearer $CK:$CS" # Forma 2 (equivalente): # -H "x-consumer-key: $CK" -H "x-consumer-secret: $CS"
A4: CP-01 | B4: Ver la cola de pedidos nuevos | C4: Lo que el ERP consulta cada 10 minutos. | D4: curl -s -H "Authorization: Bearer $CK:$CS" \ "$BASE_URL/api/v1/orders/on-hold?page=1&perPage=10" | python3 -m json.tool
A5: CP-01 | B5: Tasa de cambio vigente (público) | C5: Para anotar la tasa antes de comprar. | D5: curl -s "$BASE_URL/exchange-rates/current" | python3 -m json.tool
A6: CP-02 | B6: Confirmar el pedido con la orden de compra | C6: Paso 2 del flujo del ERP. | D6: curl -s -X PUT -H "Authorization: Bearer $CK:$CS" \ -H "Content-Type: application/json" \ -d '{"status":"pending","order_key":"OC-PRUEBA-001"}' \ "$BASE_URL/api/v1/orders/{{ORDER_ID}}" | python3 -m json.tool
A7: CP-02 | B7: Confirmar por el endpoint dedicado | C7: Camino alterno, mismo efecto. | D7: curl -s -X PUT -H "Authorization: Bearer $CK:$CS" \ -H "Content-Type: application/json" \ -d '{"order_key":"OC-PRUEBA-002"}' \ "$BASE_URL/api/v1/orders/{{ORDER_ID}}/acknowledge" | python3 -m json.tool
A8: CP-03 | B8: Facturar el pedido | C8: Paso 3 del flujo. ⚠ Manda correo real al cliente. | D8: curl -s -X PUT -H "Authorization: Bearer $CK:$CS" \ -H "Content-Type: application/json" \ -d '{"status":"completed","order_key":"OC-PRUEBA-001 / FAC-0001","date_completed":"2026-08-01T15:30:00.000Z"}' \ "$BASE_URL/api/v1/orders/{{ORDER_ID}}" | python3 -m json.tool
A9: CP-04 | B9: Anular el pedido | C9: Paso 4 del flujo. Devuelve el inventario. | D9: curl -s -X PUT -H "Authorization: Bearer $CK:$CS" \ -H "Content-Type: application/json" \ -d '{"status":"cancelled","date_completed":"2026-08-01T16:00:00.000Z"}' \ "$BASE_URL/api/v1/orders/{{ORDER_ID}}" | python3 -m json.tool
A10: CP-04 | B10: Anular con la grafía de OrbisNet (una sola L) | C10: Se aceptan las dos escrituras. | D10: curl -s -X PUT -H "Authorization: Bearer $CK:$CS" \ -H "Content-Type: application/json" \ -d '{"status":"canceled","date_completed":"2026-08-01T16:05:00.000Z"}' \ "$BASE_URL/api/v1/orders/{{ORDER_ID}}" | python3 -m json.tool
A11: CP-04 | B11: Ver el inventario de un producto | C11: Para comparar el stock antes y después de anular. | D11: curl -s -H "Authorization: Bearer $CK:$CS" \ "$BASE_URL/api/v1/products/sku/{{SKU}}" \ | python3 -c "import sys,json; p=json.load(sys.stdin); print(p['sku'], p['name'], 'stock:', p['inventory'])"
A12: CP-05 | B12: Consultar un pedido por id | C12: Devuelve el formato WooCommerce. | D12: curl -s -H "Authorization: Bearer $CK:$CS" \ "$BASE_URL/api/v1/orders/{{ORDER_ID}}" | python3 -m json.tool
... A19: CP-11 | B19: Previsualizar un pedido con cupón, sin comprar | C19: El único previsualizador válido. | D19: curl -s -X POST -H "Content-Type: application/json" \ -d '{"items":[{"productUuid":"{{PRODUCT_UUID}}","quantity":2}],"discountCode":"PRUEBA10"}' \ "$BASE_URL/orders/quote" | python3 -m json.tool
A20: CP-13 | B20: Sin llave (debe dar 401) | D20: curl -s -o /dev/null -w "%{http_code}\n" "$BASE_URL/api/v1/orders/on-hold"
A21: CP-14 | B21: Llave inválida (debe dar 401) | D21: curl -s -o /dev/null -w "%{http_code}\n" \ -H "Authorization: Bearer ck_inventada:cs_inventado" \ "$BASE_URL/api/v1/orders/on-hold"
A22: CP-14 | B22: Autenticación por cabeceras separadas (debe dar 200) | D22: curl -s -o /dev/null -w "%{http_code}\n" \ -H "x-consumer-key: $CK" -H "x-consumer-secret: $CS" \ "$BASE_URL/api/v1/orders/on-hold"
A23: CP-15 | B23: Llave de solo lectura escribiendo (debe dar 403) | C23: Reemplazar CK_RO/CS_RO por la llave de solo lectura. | D23: curl -s -o /dev/null -w "%{http_code}\n" -X PUT \ -H "Authorization: Bearer {{CK_RO}}:{{CS_RO}}" \ -H "Content-Type: application/json" \ -d '{"status":"pending","order_key":"OC-SOLO-LECTURA"}' \ "$BASE_URL/api/v1/orders/{{ORDER_ID}}"
A24: CP-16 | B24: Confirmar sin order_key (debe dar 400) | D24: curl -s -X PUT -H "Authorization: Bearer $CK:$CS" \ -H "Content-Type: application/json" -d '{"status":"pending"}' \ "$BASE_URL/api/v1/orders/{{ORDER_ID}}"
A25: CP-17 | B25: Facturar sin date_completed (debe dar 400) | D25: curl -s -X PUT -H "Authorization: Bearer $CK:$CS" \ -H "Content-Type: application/json" \ -d '{"status":"completed","order_key":"FAC-0001"}' \ "$BASE_URL/api/v1/orders/{{ORDER_ID}}"
A26: CP-18 | B26: Anular sin date_completed (debe dar 400) | D26: curl -s -X PUT -H "Authorization: Bearer $CK:$CS" \ -H "Content-Type: application/json" -d '{"status":"cancelled"}' \ "$BASE_URL/api/v1/orders/{{ORDER_ID}}"
A27: CP-19 | B27: Pedido inexistente (debe dar 404) | D27: curl -s -X PUT -H "Authorization: Bearer $CK:$CS" \ -H "Content-Type: application/json" \ -d '{"status":"pending","order_key":"OC-FANTASMA"}' \ "$BASE_URL/api/v1/orders/999999"
A28: CP-20 | B28: Id no numérico y UUID en el PUT (deben dar 400) | C28: El GET sí acepta UUID; el PUT no. | D28: curl -s -o /dev/null -w "%{http_code}\n" -X PUT -H "Authorization: Bearer $CK:$CS" \ -H "Content-Type: application/json" -d '{"status":"pending","order_key":"OC-X"}' \ "$BASE_URL/api/v1/orders/abc" curl -s -o /dev/null -w "%{http_code}\n" -X PUT -H "Authorization: Bearer $CK:$CS" \ -H "Content-Type: application/json" -d '{"status":"pending","order_key":"OC-X"}' \ "$BASE_URL/api/v1/orders/{{ORDER_UUID}}"
A29: CP-21 | B29: Doble confirmación: misma O/C y O/C distinta | C29: La primera repetición da 200; con otra O/C da 400. | D29: curl -s -o /dev/null -w "1a: %{http_code}\n" -X PUT -H "Authorization: Bearer $CK:$CS" \ -H "Content-Type: application/json" -d '{"status":"pending","order_key":"OC-IDEM-01"}' \ "$BASE_URL/api/v1/orders/{{ORDER_ID}}" curl -s -o /dev/null -w "2a: %{http_code}\n" -X PUT -H "Authorization: Bearer $CK:$CS" \ -H "Content-Type: application/json" -d '{"status":"pending","order_key":"OC-IDEM-01"}' \ "$BASE_URL/api/v1/orders/{{ORDER_ID}}" curl -s -o /dev/null -w "otra O/C: %{http_code}\n" -X PUT -H "Authorization: Bearer $CK:$CS" \ -H "Content-Type: application/json" -d '{"status":"pending","order_key":"OC-IDEM-02"}' \ "$BASE_URL/api/v1/orders/{{ORDER_ID}}"
A30: CP-23 | B30: Anular dos veces y mirar el stock entre medio | C30: El inventario debe volver una sola vez. | D30: curl -s -H "Authorization: Bearer $CK:$CS" "$BASE_URL/api/v1/products/sku/{{SKU}}" \ | python3 -c "import sys,json; print('antes :', json.load(sys.stdin)['inventory'])" curl -s -o /dev/null -X PUT -H "Authorization: Bearer $CK:$CS" -H "Content-Type: application/json" \ -d '{"status":"cancelled","date_completed":"2026-08-01T17:25:00.000Z"}' \ "$BASE_URL/api/v1/orders/{{ORDER_ID}}" curl -s -H "Authorization: Bearer $CK:$CS" "$BASE_URL/api/v1/products/sku/{{SKU}}" \ | python3 -c "import sys,json; print('1a anulacion:', json.load(sys.stdin)['inventory'])" curl -s -o /dev/null -X PUT -H "Authorization: Bearer $CK:$CS" -H "Content-Type: application/json" \ -d '{"status":"cancelled","date_completed":"2026-08-01T17:25:00.000Z"}' \ "$BASE_URL/api/v1/orders/{{ORDER_ID}}" curl -s -H "Authorization: Bearer $CK:$CS" "$BASE_URL/api/v1/products/sku/{{SKU}}" \ | python3 -c "import sys,json; print('2a anulacion:', json.load(sys.stdin)['inventory'])"
A31: CP-24 | B31: Fechas mal escritas y fecha sin hora | C31: Las tres primeras dan 400; la cuarta se acepta. | D31: for F in "01/08/2026" "2026-13-45T10:00:00Z" "hoy" "2026-08-01"; do echo -n "$F -> " curl -s -o /dev/null -w "%{http_code}\n" -X PUT -H "Authorization: Bearer $CK:$CS" \ -H "Content-Type: application/json" \ -d "{\"status\":\"cancelled\",\"date_completed\":\"$F\"}" \ "$BASE_URL/api/v1/orders/{{ORDER_ID}}" done
A32: CP-25 | B32: Estado inválido, cuerpo vacío y campo de más | C32: Los tres deben dar 400. | D32: curl -s -X PUT -H "Authorization: Bearer $CK:$CS" -H "Content-Type: application/json" \ -d '{"status":"shipped","order_key":"X"}' "$BASE_URL/api/v1/orders/{{ORDER_ID}}" curl -s -X PUT -H "Authorization: Bearer $CK:$CS" -H "Content-Type: application/json" \ -d '{}' "$BASE_URL/api/v1/orders/{{ORDER_ID}}" curl -s -X PUT -H "Authorization: Bearer $CK:$CS" -H "Content-Type: application/json" \ -d '{"status":"pending","order_key":"OC-1","customer_note":"algo"}' \ "$BASE_URL/api/v1/orders/{{ORDER_ID}}"
A33: CP-26 | B33: Paginación abusiva: perPage enorme, cero y página negativa | C33: Anotar el código y el tiempo de cada una. | D33: curl -s -o /dev/null -w "perPage=100000 -> %{http_code} en %{time_total}s\n" \ -H "Authorization: Bearer $CK:$CS" "$BASE_URL/api/v1/orders/on-hold?perPage=100000" curl -s -o /dev/null -w "perPage=abc -> %{http_code}\n" \ -H "Authorization: Bearer $CK:$CS" "$BASE_URL/api/v1/orders/on-hold?perPage=abc" curl -s -w "\nperPage=0 -> %{http_code}\n" \ -H "Authorization: Bearer $CK:$CS" "$BASE_URL/api/v1/orders/on-hold?perPage=0" | head -5 curl -s -o /dev/null -w "page=0 -> %{http_code}\n" \ -H "Authorization: Bearer $CK:$CS" "$BASE_URL/api/v1/orders/on-hold?page=0&perPage=10" curl -s -o /dev/null -w "page=-1 -> %{http_code}\n" \ -H "Authorization: Bearer $CK:$CS" "$BASE_URL/api/v1/orders/on-hold?page=-1&perPage=10"
A34: CP-27 | B34: Listado general (el que el ERP NO debe usar) | C34: Devuelve el pedido crudo con datos personales. | D34: curl -s -o /dev/null -w "%{http_code} en %{time_total}s\n" \ -H "Authorization: Bearer $CK:$CS" "$BASE_URL/api/v1/orders?page=1&perPage=5"
A35: Cierre | B35: Comprobaciones en base de datos | C35: Con <N> = id del pedido de prueba. | D35: -- Los montos cuadran SELECT subtotal, tax, total, subtotal + tax = total AS cuadra, subtotal_ves, tax_ves, total_ves, subtotal_ves + tax_ves = total_ves AS cuadra_ves, exchange_rate, exchange_rate_date FROM orders WHERE id = <N>; -- Los renglones y su desglose congelado SELECT product_name, quantity, price, subtotal, base, iva, base + iva = subtotal AS cuadra_renglon FROM order_items WHERE order_id = <N>; -- Referencias del ERP SELECT order_number, status, order_key, purchase_order_key, date_completed FROM orders WHERE id = <N>;

Sheet Hallazgos
A1: ID | B1: Caso relacionado | C1: Qué pasó | D1: Severidad | E1: Responsable | F1: Estado | G1: Acordado en la reunión
A2: H-01 | B2: CP-11 | C2: El pedido que recibe el ERP no tiene ningún campo de descuento. Cuando el cliente usa un cupón, las líneas llegan ya rebajadas (el descuento se reparte proporcionalmente) y OrbisNet no puede saber que hubo cupón ni cuánto fue. Confirmar si su facturación lo necesita. | D2: Alta | F2: Abierto
A3: H-02 | B3: CP-08 / CP-09 | C3: El pedido que recibe el ERP viene sólo en dólares: no trae la tasa de cambio ni los montos en bolívares, aunque el pedido sí los tiene guardados. Si OrbisNet factura en bolívares con su propia tasa, va a facturar un monto distinto al que la tienda le mostró al cliente. | D3: Alta | F3: Abierto
A4: H-03 | B4: CP-05 / CP-20 | C4: Asimetría del contrato: GET /api/v1/orders/:id acepta el id numérico o el UUID, pero PUT sólo acepta el id numérico (con UUID responde 400). Además el UUID no aparece en ningún campo de la respuesta, así que el ERP no puede descubrirlo por su cuenta. | D4: Baja | F4: Abierto
A5: H-04 | B5: CP-26 | C5: El parámetro perPage no tiene tope: perPage=100000 devuelve todos los pedidos en on-hold en una sola consulta. Un ERP mal configurado puede degradar el servidor sin querer. | D5: Media | F5: Abierto
A6: H-05 | B6: CP-26 | C6: page y perPage no validan mínimo. Con perPage=0 el límite queda en cero (puede devolver TODO y un lastPage infinito) y con page=0 o negativa el salto queda negativo, lo que Postgres rechaza y podría subir como 500. ⚠ Verificar en vivo y anotar el comportamiento real. | D6: Media | F6: Abierto
A7: H-06 | B7: CP-15 | C7: Los permisos de las llaves no son jerárquicos: una llave de 'escritura' NO puede leer. La llave que use OrbisNet tiene que ser de 'lectura y escritura' o la mitad del flujo falla con 403. | D7: Media | F7: Abierto
A8: H-07 | B8: CP-04 | C8: El guion anterior (docs/guion-pruebas-produccion.md, paso C5) dice que al anular se envían correos al cliente y al administrador. El código no envía ninguno: las anulaciones se atienden por WhatsApp. Hay que corregir el guion para no crear una expectativa falsa en la prueba. | D8: Baja | F8: Abierto
A9: H-08 | B9: CP-24 | C9: La fecha date_completed se valida como ISO 8601 pero no en su contenido: se acepta '2026-08-01' (sin hora, se guarda como medianoche UTC = 8:00 pm del día anterior en Venezuela) y también fechas del futuro lejano. ⚠ Verificar cómo se muestran en el panel. | D9: Baja | F9: Abierto
A10: H-09 | B10: CP-14 | C10: El guard acepta las credenciales también como parámetros de la URL (?consumer_key=…&consumer_secret=…), lo que deja la llave y el secreto escritos en los registros del servidor y en el historial de peticiones. Acordar con el integrador que use sólo la cabecera. | D10: Media | F10: Abierto
A11: H-10 | B11: CP-27 | C11: GET /api/v1/orders (listado general) devuelve el pedido crudo — con cédula, dirección, correo, teléfono y datos del pago — a cualquier llave de solo lectura, y pagina en memoria después de traer TODOS los pedidos de la base. Ya estaba anotado en el guion anterior; sigue abierto. | D11: Media | F11: Abierto
A12: H-11 | B12: CP-09 | C12: Las columnas de montos en bolívares topan en Bs 99.999.999,99 (unos USD 207.800 a la tasa actual, y el techo baja cada vez que sube la tasa). Un pedido por encima de eso falla al guardar y deja filas huérfanas (dirección, ficha de invitado, datos de pago) sin pedido que las use. | D12: Baja | F12: Abierto
A13: H-12 | B13: CP-01 | C13: La cola de on-hold sólo devuelve pedidos que tengan al menos un renglón (usa un cruce obligatorio con los ítems). Un pedido sin renglones existiría en la base y el ERP nunca lo vería. Hoy no debería ocurrir, pero no hay nada que lo impida. | D13: Baja | F13: Abierto
... A16: H-15 | B16: CP-02 / CP-03 | C16: order_key no tiene restricción de unicidad: dos pedidos distintos pueden quedar con la misma orden de compra o el mismo número de factura sin que el sistema avise. | D16: Baja | F16: Abierto

Sheet Resumen
B2: Resumen de la sesión
B3: Se llena solo a partir de la hoja «Casos de prueba». No escribir nada aquí.
B5: Casos de prueba | C5: =27
B6: Pasos en total | C6: =COUNTA('Casos de prueba'!$A$2:$A$136)
B7: Pasos marcados OK | C7: =COUNTIF('Casos de prueba'!$H$2:$H$136,"X")
B8: Pasos marcados con falla | C8: =COUNTIF('Casos de prueba'!$I$2:$I$136,"X")
B9: Pasos sin probar | C9: =COUNTA('Casos de prueba'!$A$2:$A$136)-COUNTIF('Casos de prueba'!$H$2:$H$136,"X")-COUNTIF('Casos de prueba'!$I$2:$I$136,"X")+SUMPRODUCT(--('Casos de prueba'!$H$2:$H$136="X"),--('Casos de prueba'!$I$2:$I$136="X"))
B10: Pasos marcados en las dos casillas (revisar) | C10: =SUMPRODUCT(--('Casos de prueba'!$H$2:$H$136="X"),--('Casos de prueba'!$I$2:$I$136="X"))
B12: Avance (pasos probados sobre el total) | C12: =IF(COUNTA('Casos de prueba'!$A$2:$A$136)=0,0,(COUNTIF('Casos de prueba'!$H$2:$H$136,"X")+COUNTIF('Casos de prueba'!$I$2:$I$136,"X"))/COUNTA('Casos de prueba'!$A$2:$A$136))
B13: Éxito (OK sobre lo que ya se probó) | C13: =IF((COUNTIF('Casos de prueba'!$H$2:$H$136,"X")+COUNTIF('Casos de prueba'!$I$2:$I$136,"X"))=0,0,COUNTIF('Casos de prueba'!$H$2:$H$136,"X")/(COUNTIF('Casos de prueba'!$H$2:$H$136,"X")+COUNTIF('Casos de prueba'!$I$2:$I$136,"X")))
B15: Hallazgos anotados
B16: Hallazgos registrados | C16: =COUNTA(Hallazgos!$A$2:$A$36)
B17: Bloqueantes | C17: =COUNTIF(Hallazgos!$D$2:$D$36,"Bloqueante")
B18: Severidad alta | C18: =COUNTIF(Hallazgos!$D$2:$D$36,"Alta")
B19: Resueltos | C19: =COUNTIF(Hallazgos!$F$2:$F$36,"Resuelto")
B20: Abiertos | C20: =COUNTIF(Hallazgos!$F$2:$F$36,"Abierto")
B22: Por bloque
B23: Bloque | C23: Pasos | D23: OK | E23: Fallas | F23: Sin probar | G23: Avance
B24: A. Camino feliz | C24: =36 | D24: =COUNTIF('Casos de prueba'!$H$2:$H$37,"X") | E24: =COUNTIF('Casos de prueba'!$I$2:$I$37,"X") | F24: =C24-D24-E24 | G24: =IF(C24=0,0,(D24+E24)/C24)
B25: B. Verificación de montos | C25: =39 | D25: =COUNTIF('Casos de prueba'!$H$38:$H$76,"X") | E25: =COUNTIF('Casos de prueba'!$I$38:$I$76,"X") | F25: =C25-D25-E25 | G25: =IF(C25=0,0,(D25+E25)/C25)
B26: C. Errores y casos borde | C26: =60 | D26: =COUNTIF('Casos de prueba'!$H$77:$H$136,"X") | E26: =COUNTIF('Casos de prueba'!$I$77:$I$136,"X") | F26: =C26-D26-E26 | G26: =IF(C26=0,0,(D26+E26)/C26)
B28: Caso por caso
B29: Caso | C29: Pasos | D29: OK | E29: Fallas | F29: Sin probar | G29: Avance
B30: CP-01 · Nace el pedido y el ERP lo ve en la cola | C30: 8 | D30: =COUNTIF('Casos de prueba'!$H$2:$H$9,"X") | E30: =COUNTIF('Casos de prueba'!$I$2:$I$9,"X") | F30: =C30-D30-E30 | G30: =IF(C30=0,0,(D30+E30)/C30)
B31: CP-02 · El ERP confirma el pedido (registra su O/C) | C31: 5 | D31: =COUNTIF('Casos de prueba'!$H$10:$H$14,"X") | E31: =COUNTIF('Casos de prueba'!$I$10:$I$14,"X") | F31: =C31-D31-E31 | G31: =IF(C31=0,0,(D31+E31)/C31)
B32: CP-03 · El ERP factura el pedido | C32: 5 | D32: =COUNTIF('Casos de prueba'!$H$15:$H$19,"X") | E32: =COUNTIF('Casos de prueba'!$I$15:$I$19,"X") | F32: =C32-D32-E32 | G32: =IF(C32=0,0,(D32+E32)/C32)
B33: CP-04 · El ERP anula un pedido y vuelve el inventario | C33: 7 | D33: =COUNTIF('Casos de prueba'!$H$20:$H$26,"X") | E33: =COUNTIF('Casos de prueba'!$I$20:$I$26,"X") | F33: =C33-D33-E33 | G33: =IF(C33=0,0,(D33+E33)/C33)
B34: CP-05 · Consultar un pedido puntual por id y por UUID | C34: 5 | D34: =COUNTIF('Casos de prueba'!$H$27:$H$31,"X") | E34: =COUNTIF('Casos de prueba'!$I$27:$I$31,"X") | F34: =C34-D34-E34 | G34: =IF(C34=0,0,(D34+E34)/C34)
B35: CP-06 · Paginación de la cola y cabeceras Link | C35: 6 | D35: =COUNTIF('Casos de prueba'!$H$32:$H$37,"X") | E35: =COUNTIF('Casos de prueba'!$I$32:$I$37,"X") | F35: =C35-D35-E35 | G35: =IF(C35=0,0,(D35+E35)/C35)
B36: CP-07 · El total del pedido cuadra: base + IVA = total | C36: 7 | D36: =COUNTIF('Casos de prueba'!$H$38:$H$44,"X") | E36: =COUNTIF('Casos de prueba'!$I$38:$I$44,"X") | F36: =C36-D36-E36 | G36: =IF(C36=0,0,(D36+E36)/C36)
B37: CP-08 · La tasa del pedido es la vigente al momento de la compra | C37: 6 | D37: =COUNTIF('Casos de prueba'!$H$45:$H$50,"X") | E37: =COUNTIF('Casos de prueba'!$I$45:$I$50,"X") | F37: =C37-D37-E37 | G37: =IF(C37=0,0,(D37+E37)/C37)
B38: CP-09 · Los montos en bolívares cuadran con los dólares por la tasa | C38: 6 | D38: =COUNTIF('Casos de prueba'!$H$51:$H$56,"X") | E38: =COUNTIF('Casos de prueba'!$I$51:$I$56,"X") | F38: =C38-D38-E38 | G38: =IF(C38=0,0,(D38+E38)/C38)
B39: CP-10 · El desglose por ítem suma el total | C39: 6 | D39: =COUNTIF('Casos de prueba'!$H$57:$H$62,"X") | E39: =COUNTIF('Casos de prueba'!$I$57:$I$62,"X") | F39: =C39-D39-E39 | G39: =IF(C39=0,0,(D39+E39)/C39)
B40: CP-11 · Pedido con cupón de descuento | C40: 9 | D40: =COUNTIF('Casos de prueba'!$H$63:$H$71,"X") | E40: =COUNTIF('Casos de prueba'!$I$63:$I$71,"X") | F40: =C40-D40-E40 | G40: =IF(C40=0,0,(D40+E40)/C40)
B41: CP-12 · Envío a domicilio contra retiro en tienda | C41: 5 | D41: =COUNTIF('Casos de prueba'!$H$72:$H$76,"X") | E41: =COUNTIF('Casos de prueba'!$I$72:$I$76,"X") | F41: =C41-D41-E41 | G41: =IF(C41=0,0,(D41+E41)/C41)
B42: CP-13 · Llamar sin llave de API | C42: 4 | D42: =COUNTIF('Casos de prueba'!$H$77:$H$80,"X") | E42: =COUNTIF('Casos de prueba'!$I$77:$I$80,"X") | F42: =C42-D42-E42 | G42: =IF(C42=0,0,(D42+E42)/C42)
B43: CP-14 · Llamar con llave inválida o desactivada | C43: 4 | D43: =COUNTIF('Casos de prueba'!$H$81:$H$84,"X") | E43: =COUNTIF('Casos de prueba'!$I$81:$I$84,"X") | F43: =C43-D43-E43 | G43: =IF(C43=0,0,(D43+E43)/C43)
B44: CP-15 · Permisos de la llave: lectura contra escritura | C44: 4 | D44: =COUNTIF('Casos de prueba'!$H$85:$H$88,"X") | E44: =COUNTIF('Casos de prueba'!$I$85:$I$88,"X") | F44: =C44-D44-E44 | G44: =IF(C44=0,0,(D44+E44)/C44)
B45: CP-16 · Confirmar sin la orden de compra (order_key) | C45: 3 | D45: =COUNTIF('Casos de prueba'!$H$89:$H$91,"X") | E45: =COUNTIF('Casos de prueba'!$I$89:$I$91,"X") | F45: =C45-D45-E45 | G45: =IF(C45=0,0,(D45+E45)/C45)
B46: CP-17 · Facturar sin los datos obligatorios | C46: 3 | D46: =COUNTIF('Casos de prueba'!$H$92:$H$94,"X") | E46: =COUNTIF('Casos de prueba'!$I$92:$I$94,"X") | F46: =C46-D46-E46 | G46: =IF(C46=0,0,(D46+E46)/C46)
B47: CP-18 · Anular sin la fecha | C47: 3 | D47: =COUNTIF('Casos de prueba'!$H$95:$H$97,"X") | E47: =COUNTIF('Casos de prueba'!$I$95:$I$97,"X") | F47: =C47-D47-E47 | G47: =IF(C47=0,0,(D47+E47)/C47)
B48: CP-19 · Trabajar sobre un pedido que no existe | C48: 3 | D48: =COUNTIF('Casos de prueba'!$H$98:$H$100,"X") | E48: =COUNTIF('Casos de prueba'!$I$98:$I$100,"X") | F48: =C48-D48-E48 | G48: =IF(C48=0,0,(D48+E48)/C48)
B49: CP-20 · Id que no es un número | C49: 3 | D49: =COUNTIF('Casos de prueba'!$H$101:$H$103,"X") | E49: =COUNTIF('Casos de prueba'!$I$101:$I$103,"X") | F49: =C49-D49-E49 | G49: =IF(C49=0,0,(D49+E49)/C49)
B50: CP-21 · Confirmar dos veces el mismo pedido (idempotencia) | C50: 5 | D50: =COUNTIF('Casos de prueba'!$H$104:$H$108,"X") | E50: =COUNTIF('Casos de prueba'!$I$104:$I$108,"X") | F50: =C50-D50-E50 | G50: =IF(C50=0,0,(D50+E50)/C50)
B51: CP-22 · Facturar un pedido que no está en pendiente | C51: 4 | D51: =COUNTIF('Casos de prueba'!$H$109:$H$112,"X") | E51: =COUNTIF('Casos de prueba'!$I$109:$I$112,"X") | F51: =C51-D51-E51 | G51: =IF(C51=0,0,(D51+E51)/C51)
B52: CP-23 · Anular un pedido que no corresponde | C52: 4 | D52: =COUNTIF('Casos de prueba'!$H$113:$H$116,"X") | E52: =COUNTIF('Casos de prueba'!$I$113:$I$116,"X") | F52: =C52-D52-E52 | G52: =IF(C52=0,0,(D52+E52)/C52)
B53: CP-24 · Fecha de facturación mal escrita | C53: 6 | D53: =COUNTIF('Casos de prueba'!$H$117:$H$122,"X") | E53: =COUNTIF('Casos de prueba'!$I$117:$I$122,"X") | F53: =C53-D53-E53 | G53: =IF(C53=0,0,(D53+E53)/C53)
B54: CP-25 · Cuerpo del mensaje mal armado | C54: 5 | D54: =COUNTIF('Casos de prueba'!$H$123:$H$127,"X") | E54: =COUNTIF('Casos de prueba'!$I$123:$I$127,"X") | F54: =C54-D54-E54 | G54: =IF(C54=0,0,(D54+E54)/C54)
B55: CP-26 · Paginación con valores exagerados o raros | C55: 6 | D55: =COUNTIF('Casos de prueba'!$H$128:$H$133,"X") | E55: =COUNTIF('Casos de prueba'!$I$128:$I$133,"X") | F55: =C55-D55-E55 | G55: =IF(C55=0,0,(D55+E55)/C55)
B56: CP-27 · Endpoints que el ERP NO debe usar | C56: 3 | D56: =COUNTIF('Casos de prueba'!$H$134:$H$136,"X") | E56: =COUNTIF('Casos de prueba'!$I$134:$I$136,"X") | F56: =C56-D56-E56 | G56: =IF(C56=0,0,(D56+E56)/C56)
